odoo/addons/ssi_meeting_project/README.rst
odoo/addons/ssi_meeting_project/__init__.py
odoo/addons/ssi_meeting_project/__manifest__.py
odoo/addons/ssi_meeting_project/models/__init__.py
odoo/addons/ssi_meeting_project/models/calendar_event.py
odoo/addons/ssi_meeting_project/static/description/icon.png
odoo14_addon_ssi_meeting_project-14.0.1.0.0.dist-info/METADATA
odoo14_addon_ssi_meeting_project-14.0.1.0.0.dist-info/WHEEL
odoo14_addon_ssi_meeting_project-14.0.1.0.0.dist-info/top_level.txt
odoo14_addon_ssi_meeting_project-14.0.1.0.0.dist-info/RECORD
